{
  "$id": "1",
  "$values": [
    {
      "$id": "2",
      "TransactionId": "52267007-cbf1-4793-846a-cdaaa6193698",
      "TransactionType": "Transfer",
      "TransactionDate": "2023-08-31",
      "TransactionTime": "12:00:00",
      "PriorBalance": 15000,
      "TransactionAmount": 700,
      "SourceAccountNumber": 12689897,
      "TargetAccountNumber": 12689897,
      "Description": "Transfer from checking to savings account-(TRANSFER)"
    },
    {
      "$id": "3",
      "TransactionId": "6f089c31-1475-4559-ac67-8396ada2dcde",
      "TransactionType": "Transfer",
      "TransactionDate": "2023-09-30",
      "TransactionTime": "12:00:00",
      "PriorBalance": 15700,
      "TransactionAmount": 700,
      "SourceAccountNumber": 12689897,
      "TargetAccountNumber": 12689897,
      "Description": "Transfer from checking to savings account-(TRANSFER)"
    },
    {
      "$id": "4",
      "TransactionId": "f070b33e-800e-43c2-9ffc-d2ed8fdc1500",
      "TransactionType": "Transfer",
      "TransactionDate": "2023-12-10",
      "TransactionTime": "12:00:00",
      "PriorBalance": 16400,
      "TransactionAmount": 1050,
      "SourceAccountNumber": 12689897,
      "TargetAccountNumber": 12689897,
      "Description": "free overdraft protection-(TRANSFER)-(TRANSFER)"
    },
    {
      "$id": "5",
      "TransactionId": "9406ffcf-a187-44c7-884e-dd82ff958e6a",
      "TransactionType": "Transfer",
      "TransactionDate": "2024-01-31",
      "TransactionTime": "12:00:00",
      "PriorBalance": 15350,
      "TransactionAmount": 700,
      "SourceAccountNumber": 12689897,
      "TargetAccountNumber": 12689897,
      "Description": "Transfer from checking to savings account-(TRANSFER)"
    },
    {
      "$id": "6",
      "TransactionId": "692a2dea-2bfd-473b-8062-0a7564a8dc41",
      "TransactionType": "Transfer",
      "TransactionDate": "2024-02-05",
      "TransactionTime": "08:00:00",
      "PriorBalance": 16050,
      "TransactionAmount": 1400,
      "SourceAccountNumber": 12689897,
      "TargetAccountNumber": 12689897,
      "Description": "free overdraft protection-(TRANSFER)-(TRANSFER)"
    },
    {
      "$id": "7",
      "TransactionId": "a0df5e5b-f4ee-4635-b5d3-57397e1d7b7b",
      "TransactionType": "Transfer",
      "TransactionDate": "2024-03-31",
      "TransactionTime": "12:00:00",
      "PriorBalance": 14650,
      "TransactionAmount": 900,
      "SourceAccountNumber": 12689897,
      "TargetAccountNumber": 12689897,
      "Description": "Transfer from checking to savings account-(TRANSFER)"
    },
    {
      "$id": "8",
      "TransactionId": "ca04f0e7-f340-4385-ae29-4441006bd3c2",
      "TransactionType": "Transfer",
      "TransactionDate": "2024-05-13",
      "TransactionTime": "08:00:00",
      "PriorBalance": 15550,
      "TransactionAmount": 1400,
      "SourceAccountNumber": 12689897,
      "TargetAccountNumber": 12689897,
      "Description": "free overdraft protection-(TRANSFER)-(TRANSFER)"
    },
    {
      "$id": "9",
      "TransactionId": "d9549126-0773-4688-b774-7841702ae503",
      "TransactionType": "Transfer",
      "TransactionDate": "2024-07-13",
      "TransactionTime": "21:00:00",
      "PriorBalance": 14150,
      "TransactionAmount": 1179,
      "SourceAccountNumber": 12689897,
      "TargetAccountNumber": 12689897,
      "Description": "free overdraft protection-(TRANSFER)-(TRANSFER)"
    },
    {
      "$id": "10",
      "TransactionId": "e265b9ea-f7f4-4d77-86f6-0de7ca4765ee",
      "TransactionType": "Transfer",
      "TransactionDate": "2024-09-16",
      "TransactionTime": "08:00:00",
      "PriorBalance": 12971,
      "TransactionAmount": 1400,
      "SourceAccountNumber": 12689897,
      "TargetAccountNumber": 12689897,
      "Description": "free overdraft protection-(TRANSFER)-(TRANSFER)"
    },
    {
      "$id": "11",
      "TransactionId": "bdac46a1-4194-4505-8181-35cb68ea0fff",
      "TransactionType": "Transfer",
      "TransactionDate": "2024-10-31",
      "TransactionTime": "12:00:00",
      "PriorBalance": 11571,
      "TransactionAmount": 800,
      "SourceAccountNumber": 12689897,
      "TargetAccountNumber": 12689897,
      "Description": "Transfer from checking to savings account-(TRANSFER)"
    },
    {
      "$id": "12",
      "TransactionId": "8e4de0b3-e0ce-4c4d-9017-f7e36a9eacc3",
      "TransactionType": "Transfer",
      "TransactionDate": "2025-03-10",
      "TransactionTime": "08:00:00",
      "PriorBalance": 12371,
      "TransactionAmount": 1400,
      "SourceAccountNumber": 12689897,
      "TargetAccountNumber": 12689897,
      "Description": "free overdraft protection-(TRANSFER)-(TRANSFER)"
    },
    {
      "$id": "13",
      "TransactionId": "3f70c2a2-3a95-471e-8d07-5fd76b32c8b3",
      "TransactionType": "Transfer",
      "TransactionDate": "2025-05-31",
      "TransactionTime": "12:00:00",
      "PriorBalance": 10971,
      "TransactionAmount": 700,
      "SourceAccountNumber": 12689897,
      "TargetAccountNumber": 12689897,
      "Description": "Transfer from checking to savings account-(TRANSFER)"
    },
    {
      "$id": "14",
      "TransactionId": "a4f9e0aa-1266-4f57-a12c-a8f3b5627f6f",
      "TransactionType": "Transfer",
      "TransactionDate": "2025-06-02",
      "TransactionTime": "08:00:00",
      "PriorBalance": 11671,
      "TransactionAmount": 1400,
      "SourceAccountNumber": 12689897,
      "TargetAccountNumber": 12689897,
      "Description": "free overdraft protection-(TRANSFER)-(TRANSFER)"
    },
    {
      "$id": "15",
      "TransactionId": "3ca64a3d-1799-4f6c-84dc-c141791910ab",
      "TransactionType": "Transfer",
      "TransactionDate": "2025-08-09",
      "TransactionTime": "21:00:00",
      "PriorBalance": 10271,
      "TransactionAmount": 1181,
      "SourceAccountNumber": 12689897,
      "TargetAccountNumber": 12689897,
      "Description": "free overdraft protection-(TRANSFER)-(TRANSFER)"
    }
  ]
}