{
  "$id": "1",
  "$values": [
    {
      "$id": "2",
      "TransactionId": "e8c07c20-742d-4c07-989f-0892815fb944",
      "TransactionType": "Transfer",
      "TransactionDate": "2023-08-31",
      "TransactionTime": "12:00:00",
      "PriorBalance": 15000,
      "TransactionAmount": 800,
      "SourceAccountNumber": 18455165,
      "TargetAccountNumber": 18455165,
      "Description": "Transfer from checking to savings account-(TRANSFER)"
    },
    {
      "$id": "3",
      "TransactionId": "4f6be6f6-711d-4e82-a9a0-6bb4981b38d4",
      "TransactionType": "Transfer",
      "TransactionDate": "2023-09-30",
      "TransactionTime": "12:00:00",
      "PriorBalance": 15800,
      "TransactionAmount": 800,
      "SourceAccountNumber": 18455165,
      "TargetAccountNumber": 18455165,
      "Description": "Transfer from checking to savings account-(TRANSFER)"
    },
    {
      "$id": "4",
      "TransactionId": "6df07270-2f53-4903-8497-859943a7afbe",
      "TransactionType": "Transfer",
      "TransactionDate": "2023-12-11",
      "TransactionTime": "08:00:00",
      "PriorBalance": 16600,
      "TransactionAmount": 1400,
      "SourceAccountNumber": 18455165,
      "TargetAccountNumber": 18455165,
      "Description": "free overdraft protection-(TRANSFER)-(TRANSFER)"
    },
    {
      "$id": "5",
      "TransactionId": "020a4ea4-73cf-418b-ac05-701045389813",
      "TransactionType": "Transfer",
      "TransactionDate": "2024-01-15",
      "TransactionTime": "08:00:00",
      "PriorBalance": 15200,
      "TransactionAmount": 1400,
      "SourceAccountNumber": 18455165,
      "TargetAccountNumber": 18455165,
      "Description": "free overdraft protection-(TRANSFER)-(TRANSFER)"
    },
    {
      "$id": "6",
      "TransactionId": "92474a57-17b6-4b15-83f3-409108261b02",
      "TransactionType": "Transfer",
      "TransactionDate": "2024-02-29",
      "TransactionTime": "12:00:00",
      "PriorBalance": 13800,
      "TransactionAmount": 900,
      "SourceAccountNumber": 18455165,
      "TargetAccountNumber": 18455165,
      "Description": "Transfer from checking to savings account-(TRANSFER)"
    },
    {
      "$id": "7",
      "TransactionId": "be3f5ae5-20cf-4ef8-9f12-836d9e4cb1a1",
      "TransactionType": "Transfer",
      "TransactionDate": "2024-04-15",
      "TransactionTime": "08:00:00",
      "PriorBalance": 14700,
      "TransactionAmount": 1400,
      "SourceAccountNumber": 18455165,
      "TargetAccountNumber": 18455165,
      "Description": "free overdraft protection-(TRANSFER)-(TRANSFER)"
    },
    {
      "$id": "8",
      "TransactionId": "63b4edc8-47e6-4300-bd52-8e710326805a",
      "TransactionType": "Transfer",
      "TransactionDate": "2024-05-31",
      "TransactionTime": "12:00:00",
      "PriorBalance": 13300,
      "TransactionAmount": 800,
      "SourceAccountNumber": 18455165,
      "TargetAccountNumber": 18455165,
      "Description": "Transfer from checking to savings account-(TRANSFER)"
    },
    {
      "$id": "9",
      "TransactionId": "dfe2e36f-0c17-463a-aff4-8c249740aaf9",
      "TransactionType": "Transfer",
      "TransactionDate": "2024-07-15",
      "TransactionTime": "08:00:00",
      "PriorBalance": 14100,
      "TransactionAmount": 1400,
      "SourceAccountNumber": 18455165,
      "TargetAccountNumber": 18455165,
      "Description": "free overdraft protection-(TRANSFER)-(TRANSFER)"
    },
    {
      "$id": "10",
      "TransactionId": "e23c2d27-c46d-41f2-8c42-b0d0b205b1b3",
      "TransactionType": "Transfer",
      "TransactionDate": "2024-08-31",
      "TransactionTime": "12:00:00",
      "PriorBalance": 12700,
      "TransactionAmount": 900,
      "SourceAccountNumber": 18455165,
      "TargetAccountNumber": 18455165,
      "Description": "Transfer from checking to savings account-(TRANSFER)"
    },
    {
      "$id": "11",
      "TransactionId": "4ab72268-5431-4d92-a0e7-b3a791e49816",
      "TransactionType": "Transfer",
      "TransactionDate": "2024-09-30",
      "TransactionTime": "12:00:00",
      "PriorBalance": 13600,
      "TransactionAmount": 800,
      "SourceAccountNumber": 18455165,
      "TargetAccountNumber": 18455165,
      "Description": "Transfer from checking to savings account-(TRANSFER)"
    },
    {
      "$id": "12",
      "TransactionId": "8af8a6a9-a6a3-48d3-99e3-f934c8803336",
      "TransactionType": "Transfer",
      "TransactionDate": "2024-10-14",
      "TransactionTime": "08:00:00",
      "PriorBalance": 14400,
      "TransactionAmount": 1400,
      "SourceAccountNumber": 18455165,
      "TargetAccountNumber": 18455165,
      "Description": "free overdraft protection-(TRANSFER)-(TRANSFER)"
    },
    {
      "$id": "13",
      "TransactionId": "75c2d4c0-c184-4b09-8fc9-2a7c3984b5a6",
      "TransactionType": "Transfer",
      "TransactionDate": "2024-11-30",
      "TransactionTime": "12:00:00",
      "PriorBalance": 13000,
      "TransactionAmount": 900,
      "SourceAccountNumber": 18455165,
      "TargetAccountNumber": 18455165,
      "Description": "Transfer from checking to savings account-(TRANSFER)"
    },
    {
      "$id": "14",
      "TransactionId": "e9e444d2-84a8-491b-845f-dc859076570e",
      "TransactionType": "Transfer",
      "TransactionDate": "2024-12-31",
      "TransactionTime": "12:00:00",
      "PriorBalance": 13900,
      "TransactionAmount": 700,
      "SourceAccountNumber": 18455165,
      "TargetAccountNumber": 18455165,
      "Description": "Transfer from checking to savings account-(TRANSFER)"
    },
    {
      "$id": "15",
      "TransactionId": "0d18626d-e7aa-413c-a076-88dbcd2a4d43",
      "TransactionType": "Transfer",
      "TransactionDate": "2025-01-10",
      "TransactionTime": "12:00:00",
      "PriorBalance": 14600,
      "TransactionAmount": 1050,
      "SourceAccountNumber": 18455165,
      "TargetAccountNumber": 18455165,
      "Description": "free overdraft protection-(TRANSFER)-(TRANSFER)"
    },
    {
      "$id": "16",
      "TransactionId": "d07aee85-0244-4da1-9821-7c4b0c49989e",
      "TransactionType": "Transfer",
      "TransactionDate": "2025-02-28",
      "TransactionTime": "12:00:00",
      "PriorBalance": 13550,
      "TransactionAmount": 900,
      "SourceAccountNumber": 18455165,
      "TargetAccountNumber": 18455165,
      "Description": "Transfer from checking to savings account-(TRANSFER)"
    },
    {
      "$id": "17",
      "TransactionId": "881b14f0-64b7-438a-80b3-34e2b4f1d033",
      "TransactionType": "Transfer",
      "TransactionDate": "2025-05-31",
      "TransactionTime": "12:00:00",
      "PriorBalance": 14450,
      "TransactionAmount": 800,
      "SourceAccountNumber": 18455165,
      "TargetAccountNumber": 18455165,
      "Description": "Transfer from checking to savings account-(TRANSFER)"
    },
    {
      "$id": "18",
      "TransactionId": "eca6e4b4-7343-4f94-bdf9-552e46cafa84",
      "TransactionType": "Transfer",
      "TransactionDate": "2025-06-14",
      "TransactionTime": "21:00:00",
      "PriorBalance": 15250,
      "TransactionAmount": 1196,
      "SourceAccountNumber": 18455165,
      "TargetAccountNumber": 18455165,
      "Description": "free overdraft protection-(TRANSFER)-(TRANSFER)"
    },
    {
      "$id": "19",
      "TransactionId": "76920c89-8aff-41a4-b927-295b90fec863",
      "TransactionType": "Transfer",
      "TransactionDate": "2025-08-09",
      "TransactionTime": "21:00:00",
      "PriorBalance": 14054,
      "TransactionAmount": 1168,
      "SourceAccountNumber": 18455165,
      "TargetAccountNumber": 18455165,
      "Description": "free overdraft protection-(TRANSFER)-(TRANSFER)"
    }
  ]
}