{
  "$id": "1",
  "$values": [
    {
      "$id": "2",
      "TransactionId": "03ade974-13ca-44ff-8f4e-2389fb4172f3",
      "TransactionType": "Transfer",
      "TransactionDate": "2023-08-31",
      "TransactionTime": "12:00:00",
      "PriorBalance": 15000,
      "TransactionAmount": 800,
      "SourceAccountNumber": 18455123,
      "TargetAccountNumber": 18455123,
      "Description": "Transfer from checking to savings account-(TRANSFER)"
    },
    {
      "$id": "3",
      "TransactionId": "77f5498f-9bcd-49dd-b0d5-74e94a1a0dad",
      "TransactionType": "Transfer",
      "TransactionDate": "2023-09-30",
      "TransactionTime": "12:00:00",
      "PriorBalance": 15800,
      "TransactionAmount": 700,
      "SourceAccountNumber": 18455123,
      "TargetAccountNumber": 18455123,
      "Description": "Transfer from checking to savings account-(TRANSFER)"
    },
    {
      "$id": "4",
      "TransactionId": "a29f7493-905e-4df0-94c9-ea2da6d8a852",
      "TransactionType": "Transfer",
      "TransactionDate": "2023-11-11",
      "TransactionTime": "21:00:00",
      "PriorBalance": 16500,
      "TransactionAmount": 1205,
      "SourceAccountNumber": 18455123,
      "TargetAccountNumber": 18455123,
      "Description": "free overdraft protection-(TRANSFER)-(TRANSFER)"
    },
    {
      "$id": "5",
      "TransactionId": "dd31a325-9b86-403c-9704-220898c29603",
      "TransactionType": "Transfer",
      "TransactionDate": "2023-12-29",
      "TransactionTime": "12:00:00",
      "PriorBalance": 15295,
      "TransactionAmount": 2530.25,
      "SourceAccountNumber": 18455123,
      "TargetAccountNumber": 18455123,
      "Description": "free overdraft protection-(TRANSFER)-(TRANSFER)"
    },
    {
      "$id": "6",
      "TransactionId": "1fe88114-0b26-4f45-b6ab-ac9a2641f4ae",
      "TransactionType": "Transfer",
      "TransactionDate": "2024-01-31",
      "TransactionTime": "12:00:00",
      "PriorBalance": 12764.75,
      "TransactionAmount": 900,
      "SourceAccountNumber": 18455123,
      "TargetAccountNumber": 18455123,
      "Description": "Transfer from checking to savings account-(TRANSFER)"
    },
    {
      "$id": "7",
      "TransactionId": "48e6c6df-c07a-4422-ac5f-752f1c84fffd",
      "TransactionType": "Transfer",
      "TransactionDate": "2024-04-15",
      "TransactionTime": "08:00:00",
      "PriorBalance": 13664.75,
      "TransactionAmount": 1400,
      "SourceAccountNumber": 18455123,
      "TargetAccountNumber": 18455123,
      "Description": "free overdraft protection-(TRANSFER)-(TRANSFER)"
    },
    {
      "$id": "8",
      "TransactionId": "471d2e6e-f157-464a-9d1c-be5fa2582f45",
      "TransactionType": "Transfer",
      "TransactionDate": "2024-05-31",
      "TransactionTime": "12:00:00",
      "PriorBalance": 12264.75,
      "TransactionAmount": 800,
      "SourceAccountNumber": 18455123,
      "TargetAccountNumber": 18455123,
      "Description": "Transfer from checking to savings account-(TRANSFER)"
    },
    {
      "$id": "9",
      "TransactionId": "34e723c9-d99c-41ab-96c8-35d56a1852d7",
      "TransactionType": "Transfer",
      "TransactionDate": "2024-06-30",
      "TransactionTime": "12:00:00",
      "PriorBalance": 13064.75,
      "TransactionAmount": 900,
      "SourceAccountNumber": 18455123,
      "TargetAccountNumber": 18455123,
      "Description": "Transfer from checking to savings account-(TRANSFER)"
    },
    {
      "$id": "10",
      "TransactionId": "f2c5d2f6-979c-42a9-9a24-e13edc7ad226",
      "TransactionType": "Transfer",
      "TransactionDate": "2024-07-13",
      "TransactionTime": "21:00:00",
      "PriorBalance": 13964.75,
      "TransactionAmount": 1184,
      "SourceAccountNumber": 18455123,
      "TargetAccountNumber": 18455123,
      "Description": "free overdraft protection-(TRANSFER)-(TRANSFER)"
    },
    {
      "$id": "11",
      "TransactionId": "1345231a-c46e-4d1e-a9bf-27f80acb881e",
      "TransactionType": "Transfer",
      "TransactionDate": "2024-09-16",
      "TransactionTime": "08:00:00",
      "PriorBalance": 12780.75,
      "TransactionAmount": 1400,
      "SourceAccountNumber": 18455123,
      "TargetAccountNumber": 18455123,
      "Description": "free overdraft protection-(TRANSFER)-(TRANSFER)"
    },
    {
      "$id": "12",
      "TransactionId": "38a618db-18c4-47c3-be9d-37c8e32ff657",
      "TransactionType": "Transfer",
      "TransactionDate": "2024-12-16",
      "TransactionTime": "08:00:00",
      "PriorBalance": 11380.75,
      "TransactionAmount": 1400,
      "SourceAccountNumber": 18455123,
      "TargetAccountNumber": 18455123,
      "Description": "free overdraft protection-(TRANSFER)-(TRANSFER)"
    },
    {
      "$id": "13",
      "TransactionId": "e9d7ce1f-f1d7-4cd0-8ebc-e6b65868bba9",
      "TransactionType": "Transfer",
      "TransactionDate": "2025-01-31",
      "TransactionTime": "12:00:00",
      "PriorBalance": 9980.75,
      "TransactionAmount": 800,
      "SourceAccountNumber": 18455123,
      "TargetAccountNumber": 18455123,
      "Description": "Transfer from checking to savings account-(TRANSFER)"
    },
    {
      "$id": "14",
      "TransactionId": "485c0e42-0087-48fe-ae94-9ed750dc2c8b",
      "TransactionType": "Transfer",
      "TransactionDate": "2025-04-14",
      "TransactionTime": "08:00:00",
      "PriorBalance": 10780.75,
      "TransactionAmount": 1400,
      "SourceAccountNumber": 18455123,
      "TargetAccountNumber": 18455123,
      "Description": "free overdraft protection-(TRANSFER)-(TRANSFER)"
    },
    {
      "$id": "15",
      "TransactionId": "6438bca1-41ff-4cca-a621-d1b9a33724c5",
      "TransactionType": "Transfer",
      "TransactionDate": "2025-05-31",
      "TransactionTime": "12:00:00",
      "PriorBalance": 9380.75,
      "TransactionAmount": 800,
      "SourceAccountNumber": 18455123,
      "TargetAccountNumber": 18455123,
      "Description": "Transfer from checking to savings account-(TRANSFER)"
    },
    {
      "$id": "16",
      "TransactionId": "7980f658-370a-450c-a638-da0ea7315c38",
      "TransactionType": "Transfer",
      "TransactionDate": "2025-06-16",
      "TransactionTime": "08:00:00",
      "PriorBalance": 10180.75,
      "TransactionAmount": 1400,
      "SourceAccountNumber": 18455123,
      "TargetAccountNumber": 18455123,
      "Description": "free overdraft protection-(TRANSFER)-(TRANSFER)"
    },
    {
      "$id": "17",
      "TransactionId": "5419729f-04b3-4b60-a3a7-7cae9c3704eb",
      "TransactionType": "Transfer",
      "TransactionDate": "2025-07-31",
      "TransactionTime": "12:00:00",
      "PriorBalance": 8780.75,
      "TransactionAmount": 800,
      "SourceAccountNumber": 18455123,
      "TargetAccountNumber": 18455123,
      "Description": "Transfer from checking to savings account-(TRANSFER)"
    }
  ]
}